{
  "loadEstimationPlanList": [
    {
      "date": "2022-03-01T00:00:00.000+0300",
      "lep": 35695
    },
    {
      "date": "2022-03-01T01:00:00.000+0300",
      "lep": 33825
    },
    {
      "date": "2022-03-01T02:00:00.000+0300",
      "lep": 32626
    },
    {
      "date": "2022-03-01T03:00:00.000+0300",
      "lep": 31865
    },
    {
      "date": "2022-03-01T04:00:00.000+0300",
      "lep": 31655
    },
    {
      "date": "2022-03-01T05:00:00.000+0300",
      "lep": 32069
    },
    {
      "date": "2022-03-01T06:00:00.000+0300",
      "lep": 33174
    },
    {
      "date": "2022-03-01T07:00:00.000+0300",
      "lep": 34850
    },
    {
      "date": "2022-03-01T08:00:00.000+0300",
      "lep": 40149
    },
    {
      "date": "2022-03-01T09:00:00.000+0300",
      "lep": 43077
    },
    {
      "date": "2022-03-01T10:00:00.000+0300",
      "lep": 44470
    },
    {
      "date": "2022-03-01T11:00:00.000+0300",
      "lep": 44943
    },
    {
      "date": "2022-03-01T12:00:00.000+0300",
      "lep": 43946
    },
    {
      "date": "2022-03-01T13:00:00.000+0300",
      "lep": 43700
    },
    {
      "date": "2022-03-01T14:00:00.000+0300",
      "lep": 43611
    },
    {
      "date": "2022-03-01T15:00:00.000+0300",
      "lep": 42678
    },
    {
      "date": "2022-03-01T16:00:00.000+0300",
      "lep": 42233
    },
    {
      "date": "2022-03-01T17:00:00.000+0300",
      "lep": 41789
    },
    {
      "date": "2022-03-01T18:00:00.000+0300",
      "lep": 41834
    },
    {
      "date": "2022-03-01T19:00:00.000+0300",
      "lep": 42341
    },
    {
      "date": "2022-03-01T20:00:00.000+0300",
      "lep": 41511
    },
    {
      "date": "2022-03-01T21:00:00.000+0300",
      "lep": 40192
    },
    {
      "date": "2022-03-01T22:00:00.000+0300",
      "lep": 39217
    },
    {
      "date": "2022-03-01T23:00:00.000+0300",
      "lep": 37532
    },
    {
      "date": "2022-03-02T00:00:00.000+0300",
      "lep": 35753
    },
    {
      "date": "2022-03-02T01:00:00.000+0300",
      "lep": 33827
    },
    {
      "date": "2022-03-02T02:00:00.000+0300",
      "lep": 32575
    },
    {
      "date": "2022-03-02T03:00:00.000+0300",
      "lep": 31937
    },
    {
      "date": "2022-03-02T04:00:00.000+0300",
      "lep": 31815
    },
    {
      "date": "2022-03-02T05:00:00.000+0300",
      "lep": 32072
    },
    {
      "date": "2022-03-02T06:00:00.000+0300",
      "lep": 33229
    },
    {
      "date": "2022-03-02T07:00:00.000+0300",
      "lep": 35156
    },
    {
      "date": "2022-03-02T08:00:00.000+0300",
      "lep": 40994
    },
    {
      "date": "2022-03-02T09:00:00.000+0300",
      "lep": 43773
    },
    {
      "date": "2022-03-02T10:00:00.000+0300",
      "lep": 44919
    },
    {
      "date": "2022-03-02T11:00:00.000+0300",
      "lep": 45412
    },
    {
      "date": "2022-03-02T12:00:00.000+0300",
      "lep": 44689
    },
    {
      "date": "2022-03-02T13:00:00.000+0300",
      "lep": 44821
    },
    {
      "date": "2022-03-02T14:00:00.000+0300",
      "lep": 44987
    },
    {
      "date": "2022-03-02T15:00:00.000+0300",
      "lep": 44583
    },
    {
      "date": "2022-03-02T16:00:00.000+0300",
      "lep": 44186
    },
    {
      "date": "2022-03-02T17:00:00.000+0300",
      "lep": 43699
    },
    {
      "date": "2022-03-02T18:00:00.000+0300",
      "lep": 43218
    },
    {
      "date": "2022-03-02T19:00:00.000+0300",
      "lep": 43364
    },
    {
      "date": "2022-03-02T20:00:00.000+0300",
      "lep": 42566
    },
    {
      "date": "2022-03-02T21:00:00.000+0300",
      "lep": 41244
    },
    {
      "date": "2022-03-02T22:00:00.000+0300",
      "lep": 40162
    },
    {
      "date": "2022-03-02T23:00:00.000+0300",
      "lep": 38464
    },
    {
      "date": "2022-03-03T00:00:00.000+0300",
      "lep": 36693
    },
    {
      "date": "2022-03-03T01:00:00.000+0300",
      "lep": 34838
    },
    {
      "date": "2022-03-03T02:00:00.000+0300",
      "lep": 33726
    },
    {
      "date": "2022-03-03T03:00:00.000+0300",
      "lep": 33067
    },
    {
      "date": "2022-03-03T04:00:00.000+0300",
      "lep": 32891
    },
    {
      "date": "2022-03-03T05:00:00.000+0300",
      "lep": 33190
    },
    {
      "date": "2022-03-03T06:00:00.000+0300",
      "lep": 34402
    },
    {
      "date": "2022-03-03T07:00:00.000+0300",
      "lep": 36215
    },
    {
      "date": "2022-03-03T08:00:00.000+0300",
      "lep": 42141
    },
    {
      "date": "2022-03-03T09:00:00.000+0300",
      "lep": 45241
    },
    {
      "date": "2022-03-03T10:00:00.000+0300",
      "lep": 46413
    },
    {
      "date": "2022-03-03T11:00:00.000+0300",
      "lep": 46840
    },
    {
      "date": "2022-03-03T12:00:00.000+0300",
      "lep": 45931
    },
    {
      "date": "2022-03-03T13:00:00.000+0300",
      "lep": 45942
    },
    {
      "date": "2022-03-03T14:00:00.000+0300",
      "lep": 46021
    },
    {
      "date": "2022-03-03T15:00:00.000+0300",
      "lep": 45513
    },
    {
      "date": "2022-03-03T16:00:00.000+0300",
      "lep": 45109
    },
    {
      "date": "2022-03-03T17:00:00.000+0300",
      "lep": 44541
    },
    {
      "date": "2022-03-03T18:00:00.000+0300",
      "lep": 43876
    },
    {
      "date": "2022-03-03T19:00:00.000+0300",
      "lep": 43945
    },
    {
      "date": "2022-03-03T20:00:00.000+0300",
      "lep": 43124
    },
    {
      "date": "2022-03-03T21:00:00.000+0300",
      "lep": 41735
    },
    {
      "date": "2022-03-03T22:00:00.000+0300",
      "lep": 41058
    },
    {
      "date": "2022-03-03T23:00:00.000+0300",
      "lep": 39846
    },
    {
      "date": "2022-03-04T00:00:00.000+0300",
      "lep": 35915
    },
    {
      "date": "2022-03-04T01:00:00.000+0300",
      "lep": 33994
    },
    {
      "date": "2022-03-04T02:00:00.000+0300",
      "lep": 32862
    },
    {
      "date": "2022-03-04T03:00:00.000+0300",
      "lep": 32164
    },
    {
      "date": "2022-03-04T04:00:00.000+0300",
      "lep": 31850
    },
    {
      "date": "2022-03-04T05:00:00.000+0300",
      "lep": 32283
    },
    {
      "date": "2022-03-04T06:00:00.000+0300",
      "lep": 33433
    },
    {
      "date": "2022-03-04T07:00:00.000+0300",
      "lep": 35872
    },
    {
      "date": "2022-03-04T08:00:00.000+0300",
      "lep": 41900
    },
    {
      "date": "2022-03-04T09:00:00.000+0300",
      "lep": 44600
    },
    {
      "date": "2022-03-04T10:00:00.000+0300",
      "lep": 45519
    },
    {
      "date": "2022-03-04T11:00:00.000+0300",
      "lep": 45983
    },
    {
      "date": "2022-03-04T12:00:00.000+0300",
      "lep": 45655
    },
    {
      "date": "2022-03-04T13:00:00.000+0300",
      "lep": 44806
    },
    {
      "date": "2022-03-04T14:00:00.000+0300",
      "lep": 45148
    },
    {
      "date": "2022-03-04T15:00:00.000+0300",
      "lep": 44471
    },
    {
      "date": "2022-03-04T16:00:00.000+0300",
      "lep": 44175
    },
    {
      "date": "2022-03-04T17:00:00.000+0300",
      "lep": 43420
    },
    {
      "date": "2022-03-04T18:00:00.000+0300",
      "lep": 42461
    },
    {
      "date": "2022-03-04T19:00:00.000+0300",
      "lep": 42443
    },
    {
      "date": "2022-03-04T20:00:00.000+0300",
      "lep": 41713
    },
    {
      "date": "2022-03-04T21:00:00.000+0300",
      "lep": 40174
    },
    {
      "date": "2022-03-04T22:00:00.000+0300",
      "lep": 39377
    },
    {
      "date": "2022-03-04T23:00:00.000+0300",
      "lep": 37973
    },
    {
      "date": "2022-03-05T00:00:00.000+0300",
      "lep": 35914
    },
    {
      "date": "2022-03-05T01:00:00.000+0300",
      "lep": 33822
    },
    {
      "date": "2022-03-05T02:00:00.000+0300",
      "lep": 32291
    },
    {
      "date": "2022-03-05T03:00:00.000+0300",
      "lep": 31295
    },
    {
      "date": "2022-03-05T04:00:00.000+0300",
      "lep": 30979
    },
    {
      "date": "2022-03-05T05:00:00.000+0300",
      "lep": 31150
    },
    {
      "date": "2022-03-05T06:00:00.000+0300",
      "lep": 31766
    },
    {
      "date": "2022-03-05T07:00:00.000+0300",
      "lep": 32450
    },
    {
      "date": "2022-03-05T08:00:00.000+0300",
      "lep": 36743
    },
    {
      "date": "2022-03-05T09:00:00.000+0300",
      "lep": 40278
    },
    {
      "date": "2022-03-05T10:00:00.000+0300",
      "lep": 41864
    },
    {
      "date": "2022-03-05T11:00:00.000+0300",
      "lep": 42471
    },
    {
      "date": "2022-03-05T12:00:00.000+0300",
      "lep": 41685
    },
    {
      "date": "2022-03-05T13:00:00.000+0300",
      "lep": 41437
    },
    {
      "date": "2022-03-05T14:00:00.000+0300",
      "lep": 41315
    },
    {
      "date": "2022-03-05T15:00:00.000+0300",
      "lep": 40504
    },
    {
      "date": "2022-03-05T16:00:00.000+0300",
      "lep": 39975
    },
    {
      "date": "2022-03-05T17:00:00.000+0300",
      "lep": 39286
    },
    {
      "date": "2022-03-05T18:00:00.000+0300",
      "lep": 39467
    },
    {
      "date": "2022-03-05T19:00:00.000+0300",
      "lep": 40413
    },
    {
      "date": "2022-03-05T20:00:00.000+0300",
      "lep": 39392
    },
    {
      "date": "2022-03-05T21:00:00.000+0300",
      "lep": 38776
    },
    {
      "date": "2022-03-05T22:00:00.000+0300",
      "lep": 37925
    },
    {
      "date": "2022-03-05T23:00:00.000+0300",
      "lep": 36340
    },
    {
      "date": "2022-03-06T00:00:00.000+0300",
      "lep": 34023
    },
    {
      "date": "2022-03-06T01:00:00.000+0300",
      "lep": 32522
    },
    {
      "date": "2022-03-06T02:00:00.000+0300",
      "lep": 31092
    },
    {
      "date": "2022-03-06T03:00:00.000+0300",
      "lep": 30100
    },
    {
      "date": "2022-03-06T04:00:00.000+0300",
      "lep": 29517
    },
    {
      "date": "2022-03-06T05:00:00.000+0300",
      "lep": 29349
    },
    {
      "date": "2022-03-06T06:00:00.000+0300",
      "lep": 29284
    },
    {
      "date": "2022-03-06T07:00:00.000+0300",
      "lep": 28750
    },
    {
      "date": "2022-03-06T08:00:00.000+0300",
      "lep": 30262
    },
    {
      "date": "2022-03-06T09:00:00.000+0300",
      "lep": 32490
    },
    {
      "date": "2022-03-06T10:00:00.000+0300",
      "lep": 34224
    },
    {
      "date": "2022-03-06T11:00:00.000+0300",
      "lep": 34995
    },
    {
      "date": "2022-03-06T12:00:00.000+0300",
      "lep": 35240
    },
    {
      "date": "2022-03-06T13:00:00.000+0300",
      "lep": 35622
    },
    {
      "date": "2022-03-06T14:00:00.000+0300",
      "lep": 35686
    },
    {
      "date": "2022-03-06T15:00:00.000+0300",
      "lep": 35444
    },
    {
      "date": "2022-03-06T16:00:00.000+0300",
      "lep": 35496
    },
    {
      "date": "2022-03-06T17:00:00.000+0300",
      "lep": 35738
    },
    {
      "date": "2022-03-06T18:00:00.000+0300",
      "lep": 36682
    },
    {
      "date": "2022-03-06T19:00:00.000+0300",
      "lep": 37697
    },
    {
      "date": "2022-03-06T20:00:00.000+0300",
      "lep": 37346
    },
    {
      "date": "2022-03-06T21:00:00.000+0300",
      "lep": 36638
    },
    {
      "date": "2022-03-06T22:00:00.000+0300",
      "lep": 36281
    },
    {
      "date": "2022-03-06T23:00:00.000+0300",
      "lep": 35168
    },
    {
      "date": "2022-03-07T00:00:00.000+0300",
      "lep": 32369
    },
    {
      "date": "2022-03-07T01:00:00.000+0300",
      "lep": 30838
    },
    {
      "date": "2022-03-07T02:00:00.000+0300",
      "lep": 29499
    },
    {
      "date": "2022-03-07T03:00:00.000+0300",
      "lep": 28816
    },
    {
      "date": "2022-03-07T04:00:00.000+0300",
      "lep": 28775
    },
    {
      "date": "2022-03-07T05:00:00.000+0300",
      "lep": 29319
    },
    {
      "date": "2022-03-07T06:00:00.000+0300",
      "lep": 29626
    },
    {
      "date": "2022-03-07T07:00:00.000+0300",
      "lep": 32251
    },
    {
      "date": "2022-03-07T08:00:00.000+0300",
      "lep": 38973
    },
    {
      "date": "2022-03-07T09:00:00.000+0300",
      "lep": 42168
    },
    {
      "date": "2022-03-07T10:00:00.000+0300",
      "lep": 43487
    },
    {
      "date": "2022-03-07T11:00:00.000+0300",
      "lep": 45878
    },
    {
      "date": "2022-03-07T12:00:00.000+0300",
      "lep": 44490
    },
    {
      "date": "2022-03-07T13:00:00.000+0300",
      "lep": 43297
    },
    {
      "date": "2022-03-07T14:00:00.000+0300",
      "lep": 44958
    },
    {
      "date": "2022-03-07T15:00:00.000+0300",
      "lep": 44362
    },
    {
      "date": "2022-03-07T16:00:00.000+0300",
      "lep": 43275
    },
    {
      "date": "2022-03-07T17:00:00.000+0300",
      "lep": 42041
    },
    {
      "date": "2022-03-07T18:00:00.000+0300",
      "lep": 41705
    },
    {
      "date": "2022-03-07T19:00:00.000+0300",
      "lep": 41693
    },
    {
      "date": "2022-03-07T20:00:00.000+0300",
      "lep": 41338
    },
    {
      "date": "2022-03-07T21:00:00.000+0300",
      "lep": 40090
    },
    {
      "date": "2022-03-07T22:00:00.000+0300",
      "lep": 39092
    },
    {
      "date": "2022-03-07T23:00:00.000+0300",
      "lep": 37555
    },
    {
      "date": "2022-03-08T00:00:00.000+0300",
      "lep": 33256
    },
    {
      "date": "2022-03-08T01:00:00.000+0300",
      "lep": 31826
    },
    {
      "date": "2022-03-08T02:00:00.000+0300",
      "lep": 31130
    },
    {
      "date": "2022-03-08T03:00:00.000+0300",
      "lep": 30741
    },
    {
      "date": "2022-03-08T04:00:00.000+0300",
      "lep": 30550
    },
    {
      "date": "2022-03-08T05:00:00.000+0300",
      "lep": 31020
    },
    {
      "date": "2022-03-08T06:00:00.000+0300",
      "lep": 31810
    },
    {
      "date": "2022-03-08T07:00:00.000+0300",
      "lep": 33031
    },
    {
      "date": "2022-03-08T08:00:00.000+0300",
      "lep": 39542
    },
    {
      "date": "2022-03-08T09:00:00.000+0300",
      "lep": 42895
    },
    {
      "date": "2022-03-08T10:00:00.000+0300",
      "lep": 44486
    },
    {
      "date": "2022-03-08T11:00:00.000+0300",
      "lep": 45142
    },
    {
      "date": "2022-03-08T12:00:00.000+0300",
      "lep": 44004
    },
    {
      "date": "2022-03-08T13:00:00.000+0300",
      "lep": 43772
    },
    {
      "date": "2022-03-08T14:00:00.000+0300",
      "lep": 43838
    },
    {
      "date": "2022-03-08T15:00:00.000+0300",
      "lep": 43035
    },
    {
      "date": "2022-03-08T16:00:00.000+0300",
      "lep": 42632
    },
    {
      "date": "2022-03-08T17:00:00.000+0300",
      "lep": 41988
    },
    {
      "date": "2022-03-08T18:00:00.000+0300",
      "lep": 41183
    },
    {
      "date": "2022-03-08T19:00:00.000+0300",
      "lep": 41442
    },
    {
      "date": "2022-03-08T20:00:00.000+0300",
      "lep": 40720
    },
    {
      "date": "2022-03-08T21:00:00.000+0300",
      "lep": 39506
    },
    {
      "date": "2022-03-08T22:00:00.000+0300",
      "lep": 38472
    },
    {
      "date": "2022-03-08T23:00:00.000+0300",
      "lep": 37249
    },
    {
      "date": "2022-03-09T00:00:00.000+0300",
      "lep": 34673
    },
    {
      "date": "2022-03-09T01:00:00.000+0300",
      "lep": 32741
    },
    {
      "date": "2022-03-09T02:00:00.000+0300",
      "lep": 31816
    },
    {
      "date": "2022-03-09T03:00:00.000+0300",
      "lep": 31198
    },
    {
      "date": "2022-03-09T04:00:00.000+0300",
      "lep": 31153
    },
    {
      "date": "2022-03-09T05:00:00.000+0300",
      "lep": 31619
    },
    {
      "date": "2022-03-09T06:00:00.000+0300",
      "lep": 32766
    },
    {
      "date": "2022-03-09T07:00:00.000+0300",
      "lep": 34470
    },
    {
      "date": "2022-03-09T08:00:00.000+0300",
      "lep": 40090
    },
    {
      "date": "2022-03-09T09:00:00.000+0300",
      "lep": 43274
    },
    {
      "date": "2022-03-09T10:00:00.000+0300",
      "lep": 44775
    },
    {
      "date": "2022-03-09T11:00:00.000+0300",
      "lep": 45443
    },
    {
      "date": "2022-03-09T12:00:00.000+0300",
      "lep": 44585
    },
    {
      "date": "2022-03-09T13:00:00.000+0300",
      "lep": 44813
    },
    {
      "date": "2022-03-09T14:00:00.000+0300",
      "lep": 44933
    },
    {
      "date": "2022-03-09T15:00:00.000+0300",
      "lep": 44206
    },
    {
      "date": "2022-03-09T16:00:00.000+0300",
      "lep": 43851
    },
    {
      "date": "2022-03-09T17:00:00.000+0300",
      "lep": 43110
    },
    {
      "date": "2022-03-09T18:00:00.000+0300",
      "lep": 42495
    },
    {
      "date": "2022-03-09T19:00:00.000+0300",
      "lep": 42553
    },
    {
      "date": "2022-03-09T20:00:00.000+0300",
      "lep": 41926
    },
    {
      "date": "2022-03-09T21:00:00.000+0300",
      "lep": 40718
    },
    {
      "date": "2022-03-09T22:00:00.000+0300",
      "lep": 39508
    },
    {
      "date": "2022-03-09T23:00:00.000+0300",
      "lep": 37904
    },
    {
      "date": "2022-03-10T00:00:00.000+0300",
      "lep": 35004
    },
    {
      "date": "2022-03-10T01:00:00.000+0300",
      "lep": 33145
    },
    {
      "date": "2022-03-10T02:00:00.000+0300",
      "lep": 31902
    },
    {
      "date": "2022-03-10T03:00:00.000+0300",
      "lep": 31108
    },
    {
      "date": "2022-03-10T04:00:00.000+0300",
      "lep": 30861
    },
    {
      "date": "2022-03-10T05:00:00.000+0300",
      "lep": 31090
    },
    {
      "date": "2022-03-10T06:00:00.000+0300",
      "lep": 31925
    },
    {
      "date": "2022-03-10T07:00:00.000+0300",
      "lep": 33700
    },
    {
      "date": "2022-03-10T08:00:00.000+0300",
      "lep": 40114
    },
    {
      "date": "2022-03-10T09:00:00.000+0300",
      "lep": 43454
    },
    {
      "date": "2022-03-10T10:00:00.000+0300",
      "lep": 44509
    },
    {
      "date": "2022-03-10T11:00:00.000+0300",
      "lep": 45197
    },
    {
      "date": "2022-03-10T12:00:00.000+0300",
      "lep": 44129
    },
    {
      "date": "2022-03-10T13:00:00.000+0300",
      "lep": 44196
    },
    {
      "date": "2022-03-10T14:00:00.000+0300",
      "lep": 44359
    },
    {
      "date": "2022-03-10T15:00:00.000+0300",
      "lep": 43775
    },
    {
      "date": "2022-03-10T16:00:00.000+0300",
      "lep": 43230
    },
    {
      "date": "2022-03-10T17:00:00.000+0300",
      "lep": 42347
    },
    {
      "date": "2022-03-10T18:00:00.000+0300",
      "lep": 41252
    },
    {
      "date": "2022-03-10T19:00:00.000+0300",
      "lep": 41346
    },
    {
      "date": "2022-03-10T20:00:00.000+0300",
      "lep": 40558
    },
    {
      "date": "2022-03-10T21:00:00.000+0300",
      "lep": 39616
    },
    {
      "date": "2022-03-10T22:00:00.000+0300",
      "lep": 38517
    },
    {
      "date": "2022-03-10T23:00:00.000+0300",
      "lep": 37203
    },
    {
      "date": "2022-03-11T00:00:00.000+0300",
      "lep": 35127
    },
    {
      "date": "2022-03-11T01:00:00.000+0300",
      "lep": 33454
    },
    {
      "date": "2022-03-11T02:00:00.000+0300",
      "lep": 32447
    },
    {
      "date": "2022-03-11T03:00:00.000+0300",
      "lep": 31672
    },
    {
      "date": "2022-03-11T04:00:00.000+0300",
      "lep": 31478
    },
    {
      "date": "2022-03-11T05:00:00.000+0300",
      "lep": 32042
    },
    {
      "date": "2022-03-11T06:00:00.000+0300",
      "lep": 33075
    },
    {
      "date": "2022-03-11T07:00:00.000+0300",
      "lep": 34749
    },
    {
      "date": "2022-03-11T08:00:00.000+0300",
      "lep": 40971
    },
    {
      "date": "2022-03-11T09:00:00.000+0300",
      "lep": 43998
    },
    {
      "date": "2022-03-11T10:00:00.000+0300",
      "lep": 44810
    },
    {
      "date": "2022-03-11T11:00:00.000+0300",
      "lep": 45264
    },
    {
      "date": "2022-03-11T12:00:00.000+0300",
      "lep": 43735
    },
    {
      "date": "2022-03-11T13:00:00.000+0300",
      "lep": 42776
    },
    {
      "date": "2022-03-11T14:00:00.000+0300",
      "lep": 44294
    },
    {
      "date": "2022-03-11T15:00:00.000+0300",
      "lep": 43825
    },
    {
      "date": "2022-03-11T16:00:00.000+0300",
      "lep": 43593
    },
    {
      "date": "2022-03-11T17:00:00.000+0300",
      "lep": 42894
    },
    {
      "date": "2022-03-11T18:00:00.000+0300",
      "lep": 41984
    },
    {
      "date": "2022-03-11T19:00:00.000+0300",
      "lep": 42334
    },
    {
      "date": "2022-03-11T20:00:00.000+0300",
      "lep": 41706
    },
    {
      "date": "2022-03-11T21:00:00.000+0300",
      "lep": 40751
    },
    {
      "date": "2022-03-11T22:00:00.000+0300",
      "lep": 39714
    },
    {
      "date": "2022-03-11T23:00:00.000+0300",
      "lep": 38278
    },
    {
      "date": "2022-03-12T00:00:00.000+0300",
      "lep": 35362
    },
    {
      "date": "2022-03-12T01:00:00.000+0300",
      "lep": 33080
    },
    {
      "date": "2022-03-12T02:00:00.000+0300",
      "lep": 31968
    },
    {
      "date": "2022-03-12T03:00:00.000+0300",
      "lep": 30987
    },
    {
      "date": "2022-03-12T04:00:00.000+0300",
      "lep": 30684
    },
    {
      "date": "2022-03-12T05:00:00.000+0300",
      "lep": 31121
    },
    {
      "date": "2022-03-12T06:00:00.000+0300",
      "lep": 31627
    },
    {
      "date": "2022-03-12T07:00:00.000+0300",
      "lep": 31940
    },
    {
      "date": "2022-03-12T08:00:00.000+0300",
      "lep": 36054
    },
    {
      "date": "2022-03-12T09:00:00.000+0300",
      "lep": 38701
    },
    {
      "date": "2022-03-12T10:00:00.000+0300",
      "lep": 40052
    },
    {
      "date": "2022-03-12T11:00:00.000+0300",
      "lep": 40708
    },
    {
      "date": "2022-03-12T12:00:00.000+0300",
      "lep": 40227
    },
    {
      "date": "2022-03-12T13:00:00.000+0300",
      "lep": 40184
    },
    {
      "date": "2022-03-12T14:00:00.000+0300",
      "lep": 40050
    },
    {
      "date": "2022-03-12T15:00:00.000+0300",
      "lep": 39572
    },
    {
      "date": "2022-03-12T16:00:00.000+0300",
      "lep": 39182
    },
    {
      "date": "2022-03-12T17:00:00.000+0300",
      "lep": 38800
    },
    {
      "date": "2022-03-12T18:00:00.000+0300",
      "lep": 38815
    },
    {
      "date": "2022-03-12T19:00:00.000+0300",
      "lep": 39577
    },
    {
      "date": "2022-03-12T20:00:00.000+0300",
      "lep": 39092
    },
    {
      "date": "2022-03-12T21:00:00.000+0300",
      "lep": 38253
    },
    {
      "date": "2022-03-12T22:00:00.000+0300",
      "lep": 37192
    },
    {
      "date": "2022-03-12T23:00:00.000+0300",
      "lep": 35781
    },
    {
      "date": "2022-03-13T00:00:00.000+0300",
      "lep": 33253
    },
    {
      "date": "2022-03-13T01:00:00.000+0300",
      "lep": 31595
    },
    {
      "date": "2022-03-13T02:00:00.000+0300",
      "lep": 30648
    },
    {
      "date": "2022-03-13T03:00:00.000+0300",
      "lep": 29791
    },
    {
      "date": "2022-03-13T04:00:00.000+0300",
      "lep": 29285
    },
    {
      "date": "2022-03-13T05:00:00.000+0300",
      "lep": 29302
    },
    {
      "date": "2022-03-13T06:00:00.000+0300",
      "lep": 29362
    },
    {
      "date": "2022-03-13T07:00:00.000+0300",
      "lep": 29055
    },
    {
      "date": "2022-03-13T08:00:00.000+0300",
      "lep": 30629
    },
    {
      "date": "2022-03-13T09:00:00.000+0300",
      "lep": 32831
    },
    {
      "date": "2022-03-13T10:00:00.000+0300",
      "lep": 34703
    },
    {
      "date": "2022-03-13T11:00:00.000+0300",
      "lep": 35683
    },
    {
      "date": "2022-03-13T12:00:00.000+0300",
      "lep": 35745
    },
    {
      "date": "2022-03-13T13:00:00.000+0300",
      "lep": 35868
    },
    {
      "date": "2022-03-13T14:00:00.000+0300",
      "lep": 36045
    },
    {
      "date": "2022-03-13T15:00:00.000+0300",
      "lep": 35863
    },
    {
      "date": "2022-03-13T16:00:00.000+0300",
      "lep": 35841
    },
    {
      "date": "2022-03-13T17:00:00.000+0300",
      "lep": 35810
    },
    {
      "date": "2022-03-13T18:00:00.000+0300",
      "lep": 36379
    },
    {
      "date": "2022-03-13T19:00:00.000+0300",
      "lep": 37535
    },
    {
      "date": "2022-03-13T20:00:00.000+0300",
      "lep": 37406
    },
    {
      "date": "2022-03-13T21:00:00.000+0300",
      "lep": 36886
    },
    {
      "date": "2022-03-13T22:00:00.000+0300",
      "lep": 36212
    },
    {
      "date": "2022-03-13T23:00:00.000+0300",
      "lep": 35137
    },
    {
      "date": "2022-03-14T00:00:00.000+0300",
      "lep": 32460
    },
    {
      "date": "2022-03-14T01:00:00.000+0300",
      "lep": 30537
    },
    {
      "date": "2022-03-14T02:00:00.000+0300",
      "lep": 28951
    },
    {
      "date": "2022-03-14T03:00:00.000+0300",
      "lep": 28779
    },
    {
      "date": "2022-03-14T04:00:00.000+0300",
      "lep": 28578
    },
    {
      "date": "2022-03-14T05:00:00.000+0300",
      "lep": 29214
    },
    {
      "date": "2022-03-14T06:00:00.000+0300",
      "lep": 29675
    },
    {
      "date": "2022-03-14T07:00:00.000+0300",
      "lep": 31620
    },
    {
      "date": "2022-03-14T08:00:00.000+0300",
      "lep": 38563
    },
    {
      "date": "2022-03-14T09:00:00.000+0300",
      "lep": 43334
    },
    {
      "date": "2022-03-14T10:00:00.000+0300",
      "lep": 45351
    },
    {
      "date": "2022-03-14T11:00:00.000+0300",
      "lep": 44502
    },
    {
      "date": "2022-03-14T12:00:00.000+0300",
      "lep": 43395
    },
    {
      "date": "2022-03-14T13:00:00.000+0300",
      "lep": 45663
    },
    {
      "date": "2022-03-14T14:00:00.000+0300",
      "lep": 44088
    },
    {
      "date": "2022-03-14T15:00:00.000+0300",
      "lep": 43460
    },
    {
      "date": "2022-03-14T16:00:00.000+0300",
      "lep": 42972
    },
    {
      "date": "2022-03-14T17:00:00.000+0300",
      "lep": 43973
    },
    {
      "date": "2022-03-14T18:00:00.000+0300",
      "lep": 42861
    },
    {
      "date": "2022-03-14T19:00:00.000+0300",
      "lep": 41935
    },
    {
      "date": "2022-03-14T20:00:00.000+0300",
      "lep": 41485
    },
    {
      "date": "2022-03-14T21:00:00.000+0300",
      "lep": 40112
    },
    {
      "date": "2022-03-14T22:00:00.000+0300",
      "lep": 39661
    },
    {
      "date": "2022-03-14T23:00:00.000+0300",
      "lep": 38285
    },
    {
      "date": "2022-03-15T00:00:00.000+0300",
      "lep": 34306
    },
    {
      "date": "2022-03-15T01:00:00.000+0300",
      "lep": 32321
    },
    {
      "date": "2022-03-15T02:00:00.000+0300",
      "lep": 31067
    },
    {
      "date": "2022-03-15T03:00:00.000+0300",
      "lep": 30367
    },
    {
      "date": "2022-03-15T04:00:00.000+0300",
      "lep": 30212
    },
    {
      "date": "2022-03-15T05:00:00.000+0300",
      "lep": 30601
    },
    {
      "date": "2022-03-15T06:00:00.000+0300",
      "lep": 31429
    },
    {
      "date": "2022-03-15T07:00:00.000+0300",
      "lep": 32652
    },
    {
      "date": "2022-03-15T08:00:00.000+0300",
      "lep": 38592
    },
    {
      "date": "2022-03-15T09:00:00.000+0300",
      "lep": 42351
    },
    {
      "date": "2022-03-15T10:00:00.000+0300",
      "lep": 44047
    },
    {
      "date": "2022-03-15T11:00:00.000+0300",
      "lep": 45120
    },
    {
      "date": "2022-03-15T12:00:00.000+0300",
      "lep": 44383
    },
    {
      "date": "2022-03-15T13:00:00.000+0300",
      "lep": 44207
    },
    {
      "date": "2022-03-15T14:00:00.000+0300",
      "lep": 44272
    },
    {
      "date": "2022-03-15T15:00:00.000+0300",
      "lep": 43487
    },
    {
      "date": "2022-03-15T16:00:00.000+0300",
      "lep": 42874
    },
    {
      "date": "2022-03-15T17:00:00.000+0300",
      "lep": 42262
    },
    {
      "date": "2022-03-15T18:00:00.000+0300",
      "lep": 41828
    },
    {
      "date": "2022-03-15T19:00:00.000+0300",
      "lep": 42784
    },
    {
      "date": "2022-03-15T20:00:00.000+0300",
      "lep": 42008
    },
    {
      "date": "2022-03-15T21:00:00.000+0300",
      "lep": 40657
    },
    {
      "date": "2022-03-15T22:00:00.000+0300",
      "lep": 39333
    },
    {
      "date": "2022-03-15T23:00:00.000+0300",
      "lep": 37635
    },
    {
      "date": "2022-03-16T00:00:00.000+0300",
      "lep": 35771
    },
    {
      "date": "2022-03-16T01:00:00.000+0300",
      "lep": 33826
    },
    {
      "date": "2022-03-16T02:00:00.000+0300",
      "lep": 32626
    },
    {
      "date": "2022-03-16T03:00:00.000+0300",
      "lep": 31963
    },
    {
      "date": "2022-03-16T04:00:00.000+0300",
      "lep": 31811
    },
    {
      "date": "2022-03-16T05:00:00.000+0300",
      "lep": 32230
    },
    {
      "date": "2022-03-16T06:00:00.000+0300",
      "lep": 33033
    },
    {
      "date": "2022-03-16T07:00:00.000+0300",
      "lep": 34979
    },
    {
      "date": "2022-03-16T08:00:00.000+0300",
      "lep": 41749
    },
    {
      "date": "2022-03-16T09:00:00.000+0300",
      "lep": 45250
    },
    {
      "date": "2022-03-16T10:00:00.000+0300",
      "lep": 46414
    },
    {
      "date": "2022-03-16T11:00:00.000+0300",
      "lep": 46870
    },
    {
      "date": "2022-03-16T12:00:00.000+0300",
      "lep": 45868
    },
    {
      "date": "2022-03-16T13:00:00.000+0300",
      "lep": 45803
    },
    {
      "date": "2022-03-16T14:00:00.000+0300",
      "lep": 45592
    },
    {
      "date": "2022-03-16T15:00:00.000+0300",
      "lep": 44678
    },
    {
      "date": "2022-03-16T16:00:00.000+0300",
      "lep": 44215
    },
    {
      "date": "2022-03-16T17:00:00.000+0300",
      "lep": 43368
    },
    {
      "date": "2022-03-16T18:00:00.000+0300",
      "lep": 42471
    },
    {
      "date": "2022-03-16T19:00:00.000+0300",
      "lep": 43413
    },
    {
      "date": "2022-03-16T20:00:00.000+0300",
      "lep": 42660
    },
    {
      "date": "2022-03-16T21:00:00.000+0300",
      "lep": 41187
    },
    {
      "date": "2022-03-16T22:00:00.000+0300",
      "lep": 39764
    },
    {
      "date": "2022-03-16T23:00:00.000+0300",
      "lep": 38162
    },
    {
      "date": "2022-03-17T00:00:00.000+0300",
      "lep": 36305
    },
    {
      "date": "2022-03-17T01:00:00.000+0300",
      "lep": 34412
    },
    {
      "date": "2022-03-17T02:00:00.000+0300",
      "lep": 33102
    },
    {
      "date": "2022-03-17T03:00:00.000+0300",
      "lep": 32183
    },
    {
      "date": "2022-03-17T04:00:00.000+0300",
      "lep": 31834
    },
    {
      "date": "2022-03-17T05:00:00.000+0300",
      "lep": 32188
    },
    {
      "date": "2022-03-17T06:00:00.000+0300",
      "lep": 33048
    },
    {
      "date": "2022-03-17T07:00:00.000+0300",
      "lep": 35052
    },
    {
      "date": "2022-03-17T08:00:00.000+0300",
      "lep": 41497
    },
    {
      "date": "2022-03-17T09:00:00.000+0300",
      "lep": 44480
    },
    {
      "date": "2022-03-17T10:00:00.000+0300",
      "lep": 45250
    },
    {
      "date": "2022-03-17T11:00:00.000+0300",
      "lep": 45571
    },
    {
      "date": "2022-03-17T12:00:00.000+0300",
      "lep": 44848
    },
    {
      "date": "2022-03-17T13:00:00.000+0300",
      "lep": 44791
    },
    {
      "date": "2022-03-17T14:00:00.000+0300",
      "lep": 44707
    },
    {
      "date": "2022-03-17T15:00:00.000+0300",
      "lep": 44069
    },
    {
      "date": "2022-03-17T16:00:00.000+0300",
      "lep": 43739
    },
    {
      "date": "2022-03-17T17:00:00.000+0300",
      "lep": 43234
    },
    {
      "date": "2022-03-17T18:00:00.000+0300",
      "lep": 42480
    },
    {
      "date": "2022-03-17T19:00:00.000+0300",
      "lep": 42957
    },
    {
      "date": "2022-03-17T20:00:00.000+0300",
      "lep": 42411
    },
    {
      "date": "2022-03-17T21:00:00.000+0300",
      "lep": 41473
    },
    {
      "date": "2022-03-17T22:00:00.000+0300",
      "lep": 40358
    },
    {
      "date": "2022-03-17T23:00:00.000+0300",
      "lep": 38919
    },
    {
      "date": "2022-03-18T00:00:00.000+0300",
      "lep": 35693
    },
    {
      "date": "2022-03-18T01:00:00.000+0300",
      "lep": 34071
    },
    {
      "date": "2022-03-18T02:00:00.000+0300",
      "lep": 32960
    },
    {
      "date": "2022-03-18T03:00:00.000+0300",
      "lep": 32324
    },
    {
      "date": "2022-03-18T04:00:00.000+0300",
      "lep": 32069
    },
    {
      "date": "2022-03-18T05:00:00.000+0300",
      "lep": 32507
    },
    {
      "date": "2022-03-18T06:00:00.000+0300",
      "lep": 33332
    },
    {
      "date": "2022-03-18T07:00:00.000+0300",
      "lep": 34894
    },
    {
      "date": "2022-03-18T08:00:00.000+0300",
      "lep": 41224
    },
    {
      "date": "2022-03-18T09:00:00.000+0300",
      "lep": 44656
    },
    {
      "date": "2022-03-18T10:00:00.000+0300",
      "lep": 45719
    },
    {
      "date": "2022-03-18T11:00:00.000+0300",
      "lep": 46342
    },
    {
      "date": "2022-03-18T12:00:00.000+0300",
      "lep": 45128
    },
    {
      "date": "2022-03-18T13:00:00.000+0300",
      "lep": 44423
    },
    {
      "date": "2022-03-18T14:00:00.000+0300",
      "lep": 45131
    },
    {
      "date": "2022-03-18T15:00:00.000+0300",
      "lep": 44264
    },
    {
      "date": "2022-03-18T16:00:00.000+0300",
      "lep": 43830
    },
    {
      "date": "2022-03-18T17:00:00.000+0300",
      "lep": 43231
    },
    {
      "date": "2022-03-18T18:00:00.000+0300",
      "lep": 42150
    },
    {
      "date": "2022-03-18T19:00:00.000+0300",
      "lep": 42654
    },
    {
      "date": "2022-03-18T20:00:00.000+0300",
      "lep": 42023
    },
    {
      "date": "2022-03-18T21:00:00.000+0300",
      "lep": 41004
    },
    {
      "date": "2022-03-18T22:00:00.000+0300",
      "lep": 40014
    },
    {
      "date": "2022-03-18T23:00:00.000+0300",
      "lep": 38641
    },
    {
      "date": "2022-03-19T00:00:00.000+0300",
      "lep": 35989
    },
    {
      "date": "2022-03-19T01:00:00.000+0300",
      "lep": 33920
    },
    {
      "date": "2022-03-19T02:00:00.000+0300",
      "lep": 32351
    },
    {
      "date": "2022-03-19T03:00:00.000+0300",
      "lep": 31450
    },
    {
      "date": "2022-03-19T04:00:00.000+0300",
      "lep": 31038
    },
    {
      "date": "2022-03-19T05:00:00.000+0300",
      "lep": 31250
    },
    {
      "date": "2022-03-19T06:00:00.000+0300",
      "lep": 31684
    },
    {
      "date": "2022-03-19T07:00:00.000+0300",
      "lep": 32086
    },
    {
      "date": "2022-03-19T08:00:00.000+0300",
      "lep": 36609
    },
    {
      "date": "2022-03-19T09:00:00.000+0300",
      "lep": 39664
    },
    {
      "date": "2022-03-19T10:00:00.000+0300",
      "lep": 40965
    },
    {
      "date": "2022-03-19T11:00:00.000+0300",
      "lep": 41558
    },
    {
      "date": "2022-03-19T12:00:00.000+0300",
      "lep": 41006
    },
    {
      "date": "2022-03-19T13:00:00.000+0300",
      "lep": 40892
    },
    {
      "date": "2022-03-19T14:00:00.000+0300",
      "lep": 40693
    },
    {
      "date": "2022-03-19T15:00:00.000+0300",
      "lep": 40142
    },
    {
      "date": "2022-03-19T16:00:00.000+0300",
      "lep": 39681
    },
    {
      "date": "2022-03-19T17:00:00.000+0300",
      "lep": 39229
    },
    {
      "date": "2022-03-19T18:00:00.000+0300",
      "lep": 39169
    },
    {
      "date": "2022-03-19T19:00:00.000+0300",
      "lep": 39934
    },
    {
      "date": "2022-03-19T20:00:00.000+0300",
      "lep": 39455
    },
    {
      "date": "2022-03-19T21:00:00.000+0300",
      "lep": 38336
    },
    {
      "date": "2022-03-19T22:00:00.000+0300",
      "lep": 37343
    },
    {
      "date": "2022-03-19T23:00:00.000+0300",
      "lep": 35978
    },
    {
      "date": "2022-03-20T00:00:00.000+0300",
      "lep": 33481
    },
    {
      "date": "2022-03-20T01:00:00.000+0300",
      "lep": 32033
    },
    {
      "date": "2022-03-20T02:00:00.000+0300",
      "lep": 30754
    },
    {
      "date": "2022-03-20T03:00:00.000+0300",
      "lep": 29842
    },
    {
      "date": "2022-03-20T04:00:00.000+0300",
      "lep": 29246
    },
    {
      "date": "2022-03-20T05:00:00.000+0300",
      "lep": 29035
    },
    {
      "date": "2022-03-20T06:00:00.000+0300",
      "lep": 28877
    },
    {
      "date": "2022-03-20T07:00:00.000+0300",
      "lep": 28286
    },
    {
      "date": "2022-03-20T08:00:00.000+0300",
      "lep": 30149
    },
    {
      "date": "2022-03-20T09:00:00.000+0300",
      "lep": 32607
    },
    {
      "date": "2022-03-20T10:00:00.000+0300",
      "lep": 34377
    },
    {
      "date": "2022-03-20T11:00:00.000+0300",
      "lep": 35522
    },
    {
      "date": "2022-03-20T12:00:00.000+0300",
      "lep": 35745
    },
    {
      "date": "2022-03-20T13:00:00.000+0300",
      "lep": 35941
    },
    {
      "date": "2022-03-20T14:00:00.000+0300",
      "lep": 36018
    },
    {
      "date": "2022-03-20T15:00:00.000+0300",
      "lep": 35807
    },
    {
      "date": "2022-03-20T16:00:00.000+0300",
      "lep": 35636
    },
    {
      "date": "2022-03-20T17:00:00.000+0300",
      "lep": 35738
    },
    {
      "date": "2022-03-20T18:00:00.000+0300",
      "lep": 36305
    },
    {
      "date": "2022-03-20T19:00:00.000+0300",
      "lep": 37676
    },
    {
      "date": "2022-03-20T20:00:00.000+0300",
      "lep": 37601
    },
    {
      "date": "2022-03-20T21:00:00.000+0300",
      "lep": 36876
    },
    {
      "date": "2022-03-20T22:00:00.000+0300",
      "lep": 36201
    },
    {
      "date": "2022-03-20T23:00:00.000+0300",
      "lep": 35084
    },
    {
      "date": "2022-03-21T00:00:00.000+0300",
      "lep": 30962
    },
    {
      "date": "2022-03-21T01:00:00.000+0300",
      "lep": 29256
    },
    {
      "date": "2022-03-21T02:00:00.000+0300",
      "lep": 28282
    },
    {
      "date": "2022-03-21T03:00:00.000+0300",
      "lep": 27782
    },
    {
      "date": "2022-03-21T04:00:00.000+0300",
      "lep": 27661
    },
    {
      "date": "2022-03-21T05:00:00.000+0300",
      "lep": 28048
    },
    {
      "date": "2022-03-21T06:00:00.000+0300",
      "lep": 28708
    },
    {
      "date": "2022-03-21T07:00:00.000+0300",
      "lep": 31163
    },
    {
      "date": "2022-03-21T08:00:00.000+0300",
      "lep": 38187
    },
    {
      "date": "2022-03-21T09:00:00.000+0300",
      "lep": 42613
    },
    {
      "date": "2022-03-21T10:00:00.000+0300",
      "lep": 44327
    },
    {
      "date": "2022-03-21T11:00:00.000+0300",
      "lep": 45074
    },
    {
      "date": "2022-03-21T12:00:00.000+0300",
      "lep": 44351
    },
    {
      "date": "2022-03-21T13:00:00.000+0300",
      "lep": 44335
    },
    {
      "date": "2022-03-21T14:00:00.000+0300",
      "lep": 44344
    },
    {
      "date": "2022-03-21T15:00:00.000+0300",
      "lep": 43357
    },
    {
      "date": "2022-03-21T16:00:00.000+0300",
      "lep": 42852
    },
    {
      "date": "2022-03-21T17:00:00.000+0300",
      "lep": 42011
    },
    {
      "date": "2022-03-21T18:00:00.000+0300",
      "lep": 41226
    },
    {
      "date": "2022-03-21T19:00:00.000+0300",
      "lep": 42023
    },
    {
      "date": "2022-03-21T20:00:00.000+0300",
      "lep": 41374
    },
    {
      "date": "2022-03-21T21:00:00.000+0300",
      "lep": 40019
    },
    {
      "date": "2022-03-21T22:00:00.000+0300",
      "lep": 38791
    },
    {
      "date": "2022-03-21T23:00:00.000+0300",
      "lep": 36953
    },
    {
      "date": "2022-03-22T00:00:00.000+0300",
      "lep": 34933
    },
    {
      "date": "2022-03-22T01:00:00.000+0300",
      "lep": 32871
    },
    {
      "date": "2022-03-22T02:00:00.000+0300",
      "lep": 31583
    },
    {
      "date": "2022-03-22T03:00:00.000+0300",
      "lep": 30981
    },
    {
      "date": "2022-03-22T04:00:00.000+0300",
      "lep": 30828
    },
    {
      "date": "2022-03-22T05:00:00.000+0300",
      "lep": 31480
    },
    {
      "date": "2022-03-22T06:00:00.000+0300",
      "lep": 32243
    },
    {
      "date": "2022-03-22T07:00:00.000+0300",
      "lep": 33783
    },
    {
      "date": "2022-03-22T08:00:00.000+0300",
      "lep": 40022
    },
    {
      "date": "2022-03-22T09:00:00.000+0300",
      "lep": 43483
    },
    {
      "date": "2022-03-22T10:00:00.000+0300",
      "lep": 44852
    },
    {
      "date": "2022-03-22T11:00:00.000+0300",
      "lep": 45420
    },
    {
      "date": "2022-03-22T12:00:00.000+0300",
      "lep": 44735
    },
    {
      "date": "2022-03-22T13:00:00.000+0300",
      "lep": 44552
    },
    {
      "date": "2022-03-22T14:00:00.000+0300",
      "lep": 44399
    },
    {
      "date": "2022-03-22T15:00:00.000+0300",
      "lep": 43458
    },
    {
      "date": "2022-03-22T16:00:00.000+0300",
      "lep": 43075
    },
    {
      "date": "2022-03-22T17:00:00.000+0300",
      "lep": 42620
    },
    {
      "date": "2022-03-22T18:00:00.000+0300",
      "lep": 41893
    },
    {
      "date": "2022-03-22T19:00:00.000+0300",
      "lep": 43082
    },
    {
      "date": "2022-03-22T20:00:00.000+0300",
      "lep": 42506
    },
    {
      "date": "2022-03-22T21:00:00.000+0300",
      "lep": 41153
    },
    {
      "date": "2022-03-22T22:00:00.000+0300",
      "lep": 39760
    },
    {
      "date": "2022-03-22T23:00:00.000+0300",
      "lep": 37854
    },
    {
      "date": "2022-03-23T00:00:00.000+0300",
      "lep": 34939
    },
    {
      "date": "2022-03-23T01:00:00.000+0300",
      "lep": 33118
    },
    {
      "date": "2022-03-23T02:00:00.000+0300",
      "lep": 32014
    },
    {
      "date": "2022-03-23T03:00:00.000+0300",
      "lep": 31242
    },
    {
      "date": "2022-03-23T04:00:00.000+0300",
      "lep": 31039
    },
    {
      "date": "2022-03-23T05:00:00.000+0300",
      "lep": 31382
    },
    {
      "date": "2022-03-23T06:00:00.000+0300",
      "lep": 32197
    },
    {
      "date": "2022-03-23T07:00:00.000+0300",
      "lep": 34292
    },
    {
      "date": "2022-03-23T08:00:00.000+0300",
      "lep": 41293
    },
    {
      "date": "2022-03-23T09:00:00.000+0300",
      "lep": 44728
    },
    {
      "date": "2022-03-23T10:00:00.000+0300",
      "lep": 45835
    },
    {
      "date": "2022-03-23T11:00:00.000+0300",
      "lep": 46417
    },
    {
      "date": "2022-03-23T12:00:00.000+0300",
      "lep": 45318
    },
    {
      "date": "2022-03-23T13:00:00.000+0300",
      "lep": 45214
    },
    {
      "date": "2022-03-23T14:00:00.000+0300",
      "lep": 45206
    },
    {
      "date": "2022-03-23T15:00:00.000+0300",
      "lep": 44357
    },
    {
      "date": "2022-03-23T16:00:00.000+0300",
      "lep": 43962
    },
    {
      "date": "2022-03-23T17:00:00.000+0300",
      "lep": 43224
    },
    {
      "date": "2022-03-23T18:00:00.000+0300",
      "lep": 41977
    },
    {
      "date": "2022-03-23T19:00:00.000+0300",
      "lep": 42614
    },
    {
      "date": "2022-03-23T20:00:00.000+0300",
      "lep": 42053
    },
    {
      "date": "2022-03-23T21:00:00.000+0300",
      "lep": 40932
    },
    {
      "date": "2022-03-23T22:00:00.000+0300",
      "lep": 39689
    },
    {
      "date": "2022-03-23T23:00:00.000+0300",
      "lep": 37880
    },
    {
      "date": "2022-03-24T00:00:00.000+0300",
      "lep": 35855
    },
    {
      "date": "2022-03-24T01:00:00.000+0300",
      "lep": 33846
    },
    {
      "date": "2022-03-24T02:00:00.000+0300",
      "lep": 32600
    },
    {
      "date": "2022-03-24T03:00:00.000+0300",
      "lep": 31973
    },
    {
      "date": "2022-03-24T04:00:00.000+0300",
      "lep": 31927
    },
    {
      "date": "2022-03-24T05:00:00.000+0300",
      "lep": 32509
    },
    {
      "date": "2022-03-24T06:00:00.000+0300",
      "lep": 33403
    },
    {
      "date": "2022-03-24T07:00:00.000+0300",
      "lep": 35494
    },
    {
      "date": "2022-03-24T08:00:00.000+0300",
      "lep": 42351
    },
    {
      "date": "2022-03-24T09:00:00.000+0300",
      "lep": 44976
    },
    {
      "date": "2022-03-24T10:00:00.000+0300",
      "lep": 45694
    },
    {
      "date": "2022-03-24T11:00:00.000+0300",
      "lep": 46034
    },
    {
      "date": "2022-03-24T12:00:00.000+0300",
      "lep": 44859
    },
    {
      "date": "2022-03-24T13:00:00.000+0300",
      "lep": 44675
    },
    {
      "date": "2022-03-24T14:00:00.000+0300",
      "lep": 44716
    },
    {
      "date": "2022-03-24T15:00:00.000+0300",
      "lep": 44201
    },
    {
      "date": "2022-03-24T16:00:00.000+0300",
      "lep": 43907
    },
    {
      "date": "2022-03-24T17:00:00.000+0300",
      "lep": 43202
    },
    {
      "date": "2022-03-24T18:00:00.000+0300",
      "lep": 42280
    },
    {
      "date": "2022-03-24T19:00:00.000+0300",
      "lep": 42781
    },
    {
      "date": "2022-03-24T20:00:00.000+0300",
      "lep": 42438
    },
    {
      "date": "2022-03-24T21:00:00.000+0300",
      "lep": 41268
    },
    {
      "date": "2022-03-24T22:00:00.000+0300",
      "lep": 40264
    },
    {
      "date": "2022-03-24T23:00:00.000+0300",
      "lep": 38640
    },
    {
      "date": "2022-03-25T00:00:00.000+0300",
      "lep": 35058
    },
    {
      "date": "2022-03-25T01:00:00.000+0300",
      "lep": 33363
    },
    {
      "date": "2022-03-25T02:00:00.000+0300",
      "lep": 32280
    },
    {
      "date": "2022-03-25T03:00:00.000+0300",
      "lep": 31551
    },
    {
      "date": "2022-03-25T04:00:00.000+0300",
      "lep": 31405
    },
    {
      "date": "2022-03-25T05:00:00.000+0300",
      "lep": 31904
    },
    {
      "date": "2022-03-25T06:00:00.000+0300",
      "lep": 32559
    },
    {
      "date": "2022-03-25T07:00:00.000+0300",
      "lep": 34571
    },
    {
      "date": "2022-03-25T08:00:00.000+0300",
      "lep": 40698
    },
    {
      "date": "2022-03-25T09:00:00.000+0300",
      "lep": 43457
    },
    {
      "date": "2022-03-25T10:00:00.000+0300",
      "lep": 44404
    },
    {
      "date": "2022-03-25T11:00:00.000+0300",
      "lep": 44893
    },
    {
      "date": "2022-03-25T12:00:00.000+0300",
      "lep": 43778
    },
    {
      "date": "2022-03-25T13:00:00.000+0300",
      "lep": 42662
    },
    {
      "date": "2022-03-25T14:00:00.000+0300",
      "lep": 43663
    },
    {
      "date": "2022-03-25T15:00:00.000+0300",
      "lep": 42994
    },
    {
      "date": "2022-03-25T16:00:00.000+0300",
      "lep": 42830
    },
    {
      "date": "2022-03-25T17:00:00.000+0300",
      "lep": 42091
    },
    {
      "date": "2022-03-25T18:00:00.000+0300",
      "lep": 41116
    },
    {
      "date": "2022-03-25T19:00:00.000+0300",
      "lep": 41550
    },
    {
      "date": "2022-03-25T20:00:00.000+0300",
      "lep": 41009
    },
    {
      "date": "2022-03-25T21:00:00.000+0300",
      "lep": 40053
    },
    {
      "date": "2022-03-25T22:00:00.000+0300",
      "lep": 39056
    },
    {
      "date": "2022-03-25T23:00:00.000+0300",
      "lep": 37673
    },
    {
      "date": "2022-03-26T00:00:00.000+0300",
      "lep": 35256
    },
    {
      "date": "2022-03-26T01:00:00.000+0300",
      "lep": 33316
    },
    {
      "date": "2022-03-26T02:00:00.000+0300",
      "lep": 31780
    },
    {
      "date": "2022-03-26T03:00:00.000+0300",
      "lep": 30860
    },
    {
      "date": "2022-03-26T04:00:00.000+0300",
      "lep": 30464
    },
    {
      "date": "2022-03-26T05:00:00.000+0300",
      "lep": 30940
    },
    {
      "date": "2022-03-26T06:00:00.000+0300",
      "lep": 31284
    },
    {
      "date": "2022-03-26T07:00:00.000+0300",
      "lep": 31982
    },
    {
      "date": "2022-03-26T08:00:00.000+0300",
      "lep": 36709
    },
    {
      "date": "2022-03-26T09:00:00.000+0300",
      "lep": 39499
    },
    {
      "date": "2022-03-26T10:00:00.000+0300",
      "lep": 40752
    },
    {
      "date": "2022-03-26T11:00:00.000+0300",
      "lep": 41576
    },
    {
      "date": "2022-03-26T12:00:00.000+0300",
      "lep": 40978
    },
    {
      "date": "2022-03-26T13:00:00.000+0300",
      "lep": 40729
    },
    {
      "date": "2022-03-26T14:00:00.000+0300",
      "lep": 40611
    },
    {
      "date": "2022-03-26T15:00:00.000+0300",
      "lep": 39564
    },
    {
      "date": "2022-03-26T16:00:00.000+0300",
      "lep": 38995
    },
    {
      "date": "2022-03-26T17:00:00.000+0300",
      "lep": 38629
    },
    {
      "date": "2022-03-26T18:00:00.000+0300",
      "lep": 38543
    },
    {
      "date": "2022-03-26T19:00:00.000+0300",
      "lep": 40022
    },
    {
      "date": "2022-03-26T20:00:00.000+0300",
      "lep": 39660
    },
    {
      "date": "2022-03-26T21:00:00.000+0300",
      "lep": 38434
    },
    {
      "date": "2022-03-26T22:00:00.000+0300",
      "lep": 37308
    },
    {
      "date": "2022-03-26T23:00:00.000+0300",
      "lep": 35874
    },
    {
      "date": "2022-03-27T00:00:00.000+0300",
      "lep": 34192
    },
    {
      "date": "2022-03-27T01:00:00.000+0300",
      "lep": 32162
    },
    {
      "date": "2022-03-27T02:00:00.000+0300",
      "lep": 30178
    },
    {
      "date": "2022-03-27T03:00:00.000+0300",
      "lep": 29118
    },
    {
      "date": "2022-03-27T04:00:00.000+0300",
      "lep": 28251
    },
    {
      "date": "2022-03-27T05:00:00.000+0300",
      "lep": 28736
    },
    {
      "date": "2022-03-27T06:00:00.000+0300",
      "lep": 28731
    },
    {
      "date": "2022-03-27T07:00:00.000+0300",
      "lep": 28341
    },
    {
      "date": "2022-03-27T08:00:00.000+0300",
      "lep": 30668
    },
    {
      "date": "2022-03-27T09:00:00.000+0300",
      "lep": 32577
    },
    {
      "date": "2022-03-27T10:00:00.000+0300",
      "lep": 34080
    },
    {
      "date": "2022-03-27T11:00:00.000+0300",
      "lep": 34908
    },
    {
      "date": "2022-03-27T12:00:00.000+0300",
      "lep": 35193
    },
    {
      "date": "2022-03-27T13:00:00.000+0300",
      "lep": 35159
    },
    {
      "date": "2022-03-27T14:00:00.000+0300",
      "lep": 35001
    },
    {
      "date": "2022-03-27T15:00:00.000+0300",
      "lep": 34710
    },
    {
      "date": "2022-03-27T16:00:00.000+0300",
      "lep": 34695
    },
    {
      "date": "2022-03-27T17:00:00.000+0300",
      "lep": 35022
    },
    {
      "date": "2022-03-27T18:00:00.000+0300",
      "lep": 35565
    },
    {
      "date": "2022-03-27T19:00:00.000+0300",
      "lep": 37475
    },
    {
      "date": "2022-03-27T20:00:00.000+0300",
      "lep": 37527
    },
    {
      "date": "2022-03-27T21:00:00.000+0300",
      "lep": 36832
    },
    {
      "date": "2022-03-27T22:00:00.000+0300",
      "lep": 36153
    },
    {
      "date": "2022-03-27T23:00:00.000+0300",
      "lep": 34766
    },
    {
      "date": "2022-03-28T00:00:00.000+0300",
      "lep": 32968
    },
    {
      "date": "2022-03-28T01:00:00.000+0300",
      "lep": 30949
    },
    {
      "date": "2022-03-28T02:00:00.000+0300",
      "lep": 29723
    },
    {
      "date": "2022-03-28T03:00:00.000+0300",
      "lep": 29045
    },
    {
      "date": "2022-03-28T04:00:00.000+0300",
      "lep": 29015
    },
    {
      "date": "2022-03-28T05:00:00.000+0300",
      "lep": 29695
    },
    {
      "date": "2022-03-28T06:00:00.000+0300",
      "lep": 30579
    },
    {
      "date": "2022-03-28T07:00:00.000+0300",
      "lep": 33037
    },
    {
      "date": "2022-03-28T08:00:00.000+0300",
      "lep": 40379
    },
    {
      "date": "2022-03-28T09:00:00.000+0300",
      "lep": 43684
    },
    {
      "date": "2022-03-28T10:00:00.000+0300",
      "lep": 44779
    },
    {
      "date": "2022-03-28T11:00:00.000+0300",
      "lep": 45231
    },
    {
      "date": "2022-03-28T12:00:00.000+0300",
      "lep": 43771
    },
    {
      "date": "2022-03-28T13:00:00.000+0300",
      "lep": 43367
    },
    {
      "date": "2022-03-28T14:00:00.000+0300",
      "lep": 43397
    },
    {
      "date": "2022-03-28T15:00:00.000+0300",
      "lep": 42543
    },
    {
      "date": "2022-03-28T16:00:00.000+0300",
      "lep": 41834
    },
    {
      "date": "2022-03-28T17:00:00.000+0300",
      "lep": 41185
    },
    {
      "date": "2022-03-28T18:00:00.000+0300",
      "lep": 40623
    },
    {
      "date": "2022-03-28T19:00:00.000+0300",
      "lep": 42212
    },
    {
      "date": "2022-03-28T20:00:00.000+0300",
      "lep": 42251
    },
    {
      "date": "2022-03-28T21:00:00.000+0300",
      "lep": 41026
    },
    {
      "date": "2022-03-28T22:00:00.000+0300",
      "lep": 39831
    },
    {
      "date": "2022-03-28T23:00:00.000+0300",
      "lep": 38077
    },
    {
      "date": "2022-03-29T00:00:00.000+0300",
      "lep": 34978
    },
    {
      "date": "2022-03-29T01:00:00.000+0300",
      "lep": 33133
    },
    {
      "date": "2022-03-29T02:00:00.000+0300",
      "lep": 31956
    },
    {
      "date": "2022-03-29T03:00:00.000+0300",
      "lep": 31185
    },
    {
      "date": "2022-03-29T04:00:00.000+0300",
      "lep": 30935
    },
    {
      "date": "2022-03-29T05:00:00.000+0300",
      "lep": 31242
    },
    {
      "date": "2022-03-29T06:00:00.000+0300",
      "lep": 32020
    },
    {
      "date": "2022-03-29T07:00:00.000+0300",
      "lep": 33800
    },
    {
      "date": "2022-03-29T08:00:00.000+0300",
      "lep": 39564
    },
    {
      "date": "2022-03-29T09:00:00.000+0300",
      "lep": 42219
    },
    {
      "date": "2022-03-29T10:00:00.000+0300",
      "lep": 43394
    },
    {
      "date": "2022-03-29T11:00:00.000+0300",
      "lep": 43896
    },
    {
      "date": "2022-03-29T12:00:00.000+0300",
      "lep": 42851
    },
    {
      "date": "2022-03-29T13:00:00.000+0300",
      "lep": 42500
    },
    {
      "date": "2022-03-29T14:00:00.000+0300",
      "lep": 42121
    },
    {
      "date": "2022-03-29T15:00:00.000+0300",
      "lep": 41340
    },
    {
      "date": "2022-03-29T16:00:00.000+0300",
      "lep": 40835
    },
    {
      "date": "2022-03-29T17:00:00.000+0300",
      "lep": 40394
    },
    {
      "date": "2022-03-29T18:00:00.000+0300",
      "lep": 40027
    },
    {
      "date": "2022-03-29T19:00:00.000+0300",
      "lep": 41329
    },
    {
      "date": "2022-03-29T20:00:00.000+0300",
      "lep": 41300
    },
    {
      "date": "2022-03-29T21:00:00.000+0300",
      "lep": 40076
    },
    {
      "date": "2022-03-29T22:00:00.000+0300",
      "lep": 38987
    },
    {
      "date": "2022-03-29T23:00:00.000+0300",
      "lep": 37305
    },
    {
      "date": "2022-03-30T00:00:00.000+0300",
      "lep": 34206
    },
    {
      "date": "2022-03-30T01:00:00.000+0300",
      "lep": 32507
    },
    {
      "date": "2022-03-30T02:00:00.000+0300",
      "lep": 31369
    },
    {
      "date": "2022-03-30T03:00:00.000+0300",
      "lep": 30618
    },
    {
      "date": "2022-03-30T04:00:00.000+0300",
      "lep": 30496
    },
    {
      "date": "2022-03-30T05:00:00.000+0300",
      "lep": 31015
    },
    {
      "date": "2022-03-30T06:00:00.000+0300",
      "lep": 31480
    },
    {
      "date": "2022-03-30T07:00:00.000+0300",
      "lep": 32945
    },
    {
      "date": "2022-03-30T08:00:00.000+0300",
      "lep": 38428
    },
    {
      "date": "2022-03-30T09:00:00.000+0300",
      "lep": 41339
    },
    {
      "date": "2022-03-30T10:00:00.000+0300",
      "lep": 42396
    },
    {
      "date": "2022-03-30T11:00:00.000+0300",
      "lep": 42895
    },
    {
      "date": "2022-03-30T12:00:00.000+0300",
      "lep": 41488
    },
    {
      "date": "2022-03-30T13:00:00.000+0300",
      "lep": 41197
    },
    {
      "date": "2022-03-30T14:00:00.000+0300",
      "lep": 41089
    },
    {
      "date": "2022-03-30T15:00:00.000+0300",
      "lep": 40248
    },
    {
      "date": "2022-03-30T16:00:00.000+0300",
      "lep": 40047
    },
    {
      "date": "2022-03-30T17:00:00.000+0300",
      "lep": 39523
    },
    {
      "date": "2022-03-30T18:00:00.000+0300",
      "lep": 38905
    },
    {
      "date": "2022-03-30T19:00:00.000+0300",
      "lep": 40264
    },
    {
      "date": "2022-03-30T20:00:00.000+0300",
      "lep": 40094
    },
    {
      "date": "2022-03-30T21:00:00.000+0300",
      "lep": 39126
    },
    {
      "date": "2022-03-30T22:00:00.000+0300",
      "lep": 37972
    },
    {
      "date": "2022-03-30T23:00:00.000+0300",
      "lep": 36091
    },
    {
      "date": "2022-03-31T00:00:00.000+0300",
      "lep": 34230
    },
    {
      "date": "2022-03-31T01:00:00.000+0300",
      "lep": 32452
    },
    {
      "date": "2022-03-31T02:00:00.000+0300",
      "lep": 31303
    },
    {
      "date": "2022-03-31T03:00:00.000+0300",
      "lep": 30676
    },
    {
      "date": "2022-03-31T04:00:00.000+0300",
      "lep": 30501
    },
    {
      "date": "2022-03-31T05:00:00.000+0300",
      "lep": 30873
    },
    {
      "date": "2022-03-31T06:00:00.000+0300",
      "lep": 31240
    },
    {
      "date": "2022-03-31T07:00:00.000+0300",
      "lep": 32666
    },
    {
      "date": "2022-03-31T08:00:00.000+0300",
      "lep": 38537
    },
    {
      "date": "2022-03-31T09:00:00.000+0300",
      "lep": 41371
    },
    {
      "date": "2022-03-31T10:00:00.000+0300",
      "lep": 42003
    },
    {
      "date": "2022-03-31T11:00:00.000+0300",
      "lep": 42344
    },
    {
      "date": "2022-03-31T12:00:00.000+0300",
      "lep": 40799
    },
    {
      "date": "2022-03-31T13:00:00.000+0300",
      "lep": 40479
    },
    {
      "date": "2022-03-31T14:00:00.000+0300",
      "lep": 40771
    },
    {
      "date": "2022-03-31T15:00:00.000+0300",
      "lep": 39936
    },
    {
      "date": "2022-03-31T16:00:00.000+0300",
      "lep": 39669
    },
    {
      "date": "2022-03-31T17:00:00.000+0300",
      "lep": 39194
    },
    {
      "date": "2022-03-31T18:00:00.000+0300",
      "lep": 38355
    },
    {
      "date": "2022-03-31T19:00:00.000+0300",
      "lep": 39494
    },
    {
      "date": "2022-03-31T20:00:00.000+0300",
      "lep": 39344
    },
    {
      "date": "2022-03-31T21:00:00.000+0300",
      "lep": 38507
    },
    {
      "date": "2022-03-31T22:00:00.000+0300",
      "lep": 37422
    },
    {
      "date": "2022-03-31T23:00:00.000+0300",
      "lep": 35940
    },
    {
      "date": "2022-04-01T00:00:00.000+0300",
      "lep": 33652
    },
    {
      "date": "2022-04-01T01:00:00.000+0300",
      "lep": 31839
    },
    {
      "date": "2022-04-01T02:00:00.000+0300",
      "lep": 30694
    },
    {
      "date": "2022-04-01T03:00:00.000+0300",
      "lep": 30068
    },
    {
      "date": "2022-04-01T04:00:00.000+0300",
      "lep": 29786
    },
    {
      "date": "2022-04-01T05:00:00.000+0300",
      "lep": 30119
    },
    {
      "date": "2022-04-01T06:00:00.000+0300",
      "lep": 30462
    },
    {
      "date": "2022-04-01T07:00:00.000+0300",
      "lep": 32163
    },
    {
      "date": "2022-04-01T08:00:00.000+0300",
      "lep": 37838
    },
    {
      "date": "2022-04-01T09:00:00.000+0300",
      "lep": 40203
    },
    {
      "date": "2022-04-01T10:00:00.000+0300",
      "lep": 40658
    },
    {
      "date": "2022-04-01T11:00:00.000+0300",
      "lep": 40950
    },
    {
      "date": "2022-04-01T12:00:00.000+0300",
      "lep": 38616
    },
    {
      "date": "2022-04-01T13:00:00.000+0300",
      "lep": 37572
    },
    {
      "date": "2022-04-01T14:00:00.000+0300",
      "lep": 39021
    },
    {
      "date": "2022-04-01T15:00:00.000+0300",
      "lep": 38252
    },
    {
      "date": "2022-04-01T16:00:00.000+0300",
      "lep": 38071
    },
    {
      "date": "2022-04-01T17:00:00.000+0300",
      "lep": 37601
    },
    {
      "date": "2022-04-01T18:00:00.000+0300",
      "lep": 36651
    },
    {
      "date": "2022-04-01T19:00:00.000+0300",
      "lep": 37948
    },
    {
      "date": "2022-04-01T20:00:00.000+0300",
      "lep": 37908
    },
    {
      "date": "2022-04-01T21:00:00.000+0300",
      "lep": 36757
    },
    {
      "date": "2022-04-01T22:00:00.000+0300",
      "lep": 35658
    },
    {
      "date": "2022-04-01T23:00:00.000+0300",
      "lep": 34011
    }
  ],
  "statistics": [
    {
      "date": "2022-03-05T00:00:00.000+0300",
      "lepAvg": 37397.42,
      "lepMin": 30979,
      "lepMax": 42471,
      "lepSum": 897538
    },
    {
      "date": "2022-03-10T00:00:00.000+0300",
      "lepAvg": 38855.71,
      "lepMin": 30861,
      "lepMax": 45197,
      "lepSum": 932537
    },
    {
      "date": "2022-03-15T00:00:00.000+0300",
      "lepAvg": 38699.79,
      "lepMin": 30212,
      "lepMax": 45120,
      "lepSum": 928795
    },
    {
      "date": "2022-03-20T00:00:00.000+0300",
      "lepAvg": 33701.54,
      "lepMin": 28286,
      "lepMax": 37676,
      "lepSum": 808837
    },
    {
      "date": "2022-03-25T00:00:00.000+0300",
      "lepAvg": 38942.42,
      "lepMin": 31405,
      "lepMax": 44893,
      "lepSum": 934618
    },
    {
      "date": "2022-03-30T00:00:00.000+0300",
      "lepAvg": 37322.42,
      "lepMin": 30496,
      "lepMax": 42895,
      "lepSum": 895738
    },
    {
      "date": "2022-03-03T00:00:00.000+0300",
      "lepAvg": 40929.08,
      "lepMin": 32891,
      "lepMax": 46840,
      "lepSum": 982298
    },
    {
      "date": "2022-03-08T00:00:00.000+0300",
      "lepAvg": 38469.58,
      "lepMin": 30550,
      "lepMax": 45142,
      "lepSum": 923270
    },
    {
      "date": "2022-03-13T00:00:00.000+0300",
      "lepAvg": 33786.0,
      "lepMin": 29055,
      "lepMax": 37535,
      "lepSum": 810864
    },
    {
      "date": "2022-03-18T00:00:00.000+0300",
      "lepAvg": 39928.5,
      "lepMin": 32069,
      "lepMax": 46342,
      "lepSum": 958284
    },
    {
      "date": "2022-03-23T00:00:00.000+0300",
      "lepAvg": 39621.75,
      "lepMin": 31039,
      "lepMax": 46417,
      "lepSum": 950922
    },
    {
      "date": "2022-03-28T00:00:00.000+0300",
      "lepAvg": 38300.04,
      "lepMin": 29015,
      "lepMax": 45231,
      "lepSum": 919201
    },
    {
      "date": "2022-03-01T00:00:00.000+0300",
      "lepAvg": 39124.25,
      "lepMin": 31655,
      "lepMax": 44943,
      "lepSum": 938982
    },
    {
      "date": "2022-03-06T00:00:00.000+0300",
      "lepAvg": 33735.25,
      "lepMin": 28750,
      "lepMax": 37697,
      "lepSum": 809646
    },
    {
      "date": "2022-03-11T00:00:00.000+0300",
      "lepAvg": 39373.79,
      "lepMin": 31478,
      "lepMax": 45264,
      "lepSum": 944971
    },
    {
      "date": "2022-03-16T00:00:00.000+0300",
      "lepAvg": 40154.29,
      "lepMin": 31811,
      "lepMax": 46870,
      "lepSum": 963703
    },
    {
      "date": "2022-03-21T00:00:00.000+0300",
      "lepAvg": 37654.13,
      "lepMin": 27661,
      "lepMax": 45074,
      "lepSum": 903699
    },
    {
      "date": "2022-03-26T00:00:00.000+0300",
      "lepAvg": 36823.54,
      "lepMin": 30464,
      "lepMax": 41576,
      "lepSum": 883765
    },
    {
      "date": "2022-03-31T00:00:00.000+0300",
      "lepAvg": 37004.42,
      "lepMin": 30501,
      "lepMax": 42344,
      "lepSum": 888106
    },
    {
      "date": "2022-03-04T00:00:00.000+0300",
      "lepAvg": 39924.63,
      "lepMin": 31850,
      "lepMax": 45983,
      "lepSum": 958191
    },
    {
      "date": "2022-03-09T00:00:00.000+0300",
      "lepAvg": 39359.17,
      "lepMin": 31153,
      "lepMax": 45443,
      "lepSum": 944620
    },
    {
      "date": "2022-03-14T00:00:00.000+0300",
      "lepAvg": 38310.58,
      "lepMin": 28578,
      "lepMax": 45663,
      "lepSum": 919454
    },
    {
      "date": "2022-03-19T00:00:00.000+0300",
      "lepAvg": 37100.92,
      "lepMin": 31038,
      "lepMax": 41558,
      "lepSum": 890422
    },
    {
      "date": "2022-03-24T00:00:00.000+0300",
      "lepAvg": 39995.54,
      "lepMin": 31927,
      "lepMax": 46034,
      "lepSum": 959893
    },
    {
      "date": "2022-03-29T00:00:00.000+0300",
      "lepAvg": 38224.46,
      "lepMin": 30935,
      "lepMax": 43896,
      "lepSum": 917387
    },
    {
      "date": "2022-03-02T00:00:00.000+0300",
      "lepAvg": 39893.54,
      "lepMin": 31815,
      "lepMax": 45412,
      "lepSum": 957445
    },
    {
      "date": "2022-03-07T00:00:00.000+0300",
      "lepAvg": 38162.29,
      "lepMin": 28775,
      "lepMax": 45878,
      "lepSum": 915895
    },
    {
      "date": "2022-03-12T00:00:00.000+0300",
      "lepAvg": 36625.38,
      "lepMin": 30684,
      "lepMax": 40708,
      "lepSum": 879009
    },
    {
      "date": "2022-03-17T00:00:00.000+0300",
      "lepAvg": 39954.5,
      "lepMin": 31834,
      "lepMax": 45571,
      "lepSum": 958908
    },
    {
      "date": "2022-03-22T00:00:00.000+0300",
      "lepAvg": 39231.92,
      "lepMin": 30828,
      "lepMax": 45420,
      "lepSum": 941566
    },
    {
      "date": "2022-03-27T00:00:00.000+0300",
      "lepAvg": 33335.0,
      "lepMin": 28251,
      "lepMax": 37527,
      "lepSum": 800040
    },
    {
      "date": "2022-04-01T00:00:00.000+0300",
      "lepAvg": 35687.42,
      "lepMin": 29786,
      "lepMax": 40950,
      "lepSum": 856498
    }
  ]
}